{
  "data": {
    "article": {},
    "attachments": {},
    "author_id": "1695314246735892480",
    "conversation_id": "2067653666824503582",
    "created_at": "2026-06-18T17:00:23.000Z",
    "edit_controls": {
      "editable_until": "2026-06-18T18:00:23.000Z",
      "edits_remaining": 5,
      "is_edit_eligible": true
    },
    "edit_history_tweet_ids": [
      "2067653666824503582"
    ],
    "entities": {},
    "geo": {},
    "id": "2067653666824503582",
    "lang": "zh",
    "note_tweet": {
      "entities": {}
    },
    "possibly_sensitive": false,
    "public_metrics": {
      "bookmark_count": 0,
      "impression_count": 0,
      "like_count": 0,
      "quote_count": 0,
      "reply_count": 0,
      "retweet_count": 0
    },
    "reply_settings": "everyone",
    "text": "又因为很小的事自我怀疑了，我好焦虑，我想喊叫，我想砸东西，但是我不能，我一直在喘，喘的我脸麻，我好想和别人一样厉害，可是我没时间了，我太害怕失败了，我现在无力维持人形了，我想不到任何办法了，好难，可能我注定会失败吧"
  },
  "includes": {
    "tweets": [
      {
        "article": {},
        "attachments": {},
        "author_id": "1695314246735892480",
        "conversation_id": "2067653666824503582",
        "created_at": "2026-06-18T17:00:23.000Z",
        "edit_controls": {
          "editable_until": "2026-06-18T18:00:23.000Z",
          "edits_remaining": 5,
          "is_edit_eligible": true
        },
        "edit_history_tweet_ids": [
          "2067653666824503582"
        ],
        "entities": {},
        "geo": {},
        "id": "2067653666824503582",
        "lang": "zh",
        "note_tweet": {
          "entities": {}
        },
        "possibly_sensitive": false,
        "public_metrics": {
          "bookmark_count": 0,
          "impression_count": 0,
          "like_count": 0,
          "quote_count": 0,
          "reply_count": 0,
          "retweet_count": 0
        },
        "reply_settings": "everyone",
        "text": "又因为很小的事自我怀疑了，我好焦虑，我想喊叫，我想砸东西，但是我不能，我一直在喘，喘的我脸麻，我好想和别人一样厉害，可是我没时间了，我太害怕失败了，我现在无力维持人形了，我想不到任何办法了，好难，可能我注定会失败吧"
      }
    ],
    "users": [
      {
        "created_at": "2023-08-26T05:56:39.000Z",
        "description": "04年/大四休学/喜欢打游戏/喜欢负能量/intj/不o不割不健全/低精力/自毁倾向/友全部❤️peace &love❤️/避难小号@hahahaha131519",
        "entities": {
          "description": {
            "mentions": [
              {
                "end": 81,
                "start": 66,
                "username": "hahahaha131519"
              }
            ]
          },
          "url": {
            "urls": [
              {
                "display_url": "ngl.link/szfx1231",
                "end": 23,
                "expanded_url": "https://ngl.link/szfx1231",
                "start": 0,
                "url": "https://t.co/KWFt5Qz9Kv"
              }
            ]
          }
        },
        "id": "1695314246735892480",
        "location": "虚空",
        "name": "神之飞雪",
        "profile_image_url": "https://pbs.twimg.com/profile_images/2059490365628129280/N7sFZh1L_normal.jpg",
        "protected": false,
        "public_metrics": {
          "followers_count": 142,
          "following_count": 210,
          "like_count": 11622,
          "listed_count": 0,
          "media_count": 75,
          "tweet_count": 525
        },
        "url": "https://t.co/KWFt5Qz9Kv",
        "username": "szfx123",
        "verified": false
      }
    ]
  }
}